{
    "members": [{
            "name": "2021+: WHAT’S COMING NEXT?",
            "avatar": "https://image.freepik.com/free-vector/happy-new-year-greeting-card-with-with-2021-white-numbers-shape-christmas-ball-orange_1017-28831.jpg",
            "date": "8th , August, 2020",
            "author": "Tim Akano",
            "content": "In solitude, the mind gains strength and learns to lean upon itself. On the other side of the storm is the strength that comes from having navigated through it."
        },
        {
            "name": "AS AMERICA’S SKY GETS DARK",
            "avatar": "https://image.freepik.com/free-vector/grunge-american-flag_1102-1132.jpg",
            "date": "27th September, 2020",
            "author": "Tim Akano",
            "content": "All empires fall, eventually. But why? It’s not for lack of power. In fact, it seems to be the opposite. Their power lulls them into comfort."
        },
        {
            "name": "STABILITY IN THE STORM",
            "avatar": "https://image.freepik.com/free-vector/realistic-lightning-bolts-flashes-composition-with-view-night-city-sky-with-clouds-thunderbolt-images_1284-28574.jpg",
            "date": "28th June 2020",
            "author": "Tim Akano",
            "content": "It is not the strongest or the most intelligent who will survive but those who can best manage change"
        },
        {
            "name": "The Collapsing World Bridge",
            "avatar": "https://image.freepik.com/free-photo/sunrise-vasco-da-gama-bridge-lisbon-portugal_268835-1338.jpg",
            "date": "31st May, 2020",
            "author": "Tim Akano",
            "content": "The bridge of peace is collapsing and the bridge of war is now under construction, perhaps at faster rate than the collapse of the bridge of peace."
        },
        {
            "name": "THE SANDS ARE SHIFTING… 1",
            "avatar": "https://image.freepik.com/free-photo/change-word-wooden-background_23-2148227738.jpg",
            "date": "29th November, 2020",
            "author": "Tim Akano",
            "content": "Life is a desert of shifting sand dunes. Unpredictable. Erratic. Harmony changes into dissonance, the immediate outlives the profound, esoteric becomes clichéd."
        },
        {
            "name": "Finding the 18th Duck…or Finding the Steve Jobs’ Way",
            "avatar": "https://image.freepik.com/free-vector/old-treasure-map-with-islands-caribbean-sea_8071-3991.jpg",
            "date": "1st October, 2021",
            "author": "Tim Akano",
            "content": "Crisis equals opportunity. And difficult roads often lead to amazing destinations. Always? Sometimes?"
        },
        {
            "name": "Collaboration vs Total Ownership Mentality -TOM",
            "avatar": "https://image.freepik.com/free-photo/business-people-clapping-hands-together_53876-14938.jpg",
            "date": "12th October, 2021",
            "author": "Tim Akano",
            "content": "How come 18 African billionaires made the Forbes 2021 ranking list of the world's richest people but there is no single African-owned company on the 2021 Fortune Global 500 companies ranking?"
        },
        {
            "name": "The Game of Life & The 3 Teams Featuring",
            "avatar": "https://image.freepik.com/free-photo/clock-beach-time-business-concept_1204-346.jpg",
            "date": "14th, October 2021",
            "author": "Tim Akano",
            "content": "Nigerians are great people but the nation is perpetually on the brink with blinking, non stop red light which signifies imminent existential threats."
        }

    ]
}